crimson/langgraph_dev_tool/__init__.py
crimson/langgraph_dev_tool/display.py
crimson_langgraph_dev_tool-0.1.0.dist-info/LICENSE
crimson_langgraph_dev_tool-0.1.0.dist-info/METADATA
crimson_langgraph_dev_tool-0.1.0.dist-info/WHEEL
crimson_langgraph_dev_tool-0.1.0.dist-info/top_level.txt
crimson_langgraph_dev_tool-0.1.0.dist-info/RECORD
