Metadata-Version: 2.2
Name: crimson-langgraph-dev-tool
Version: 0.1.0
Summary: A lightweight library for langgraph that provides useful shortcuts and additional utility functions.
Author-email: Sisung Kim <sisung.kim1@gmail.com>
Project-URL: Homepage, https://github.com/crimson206/langgraph-dev-tool
Project-URL: Bug Tracker, https://github.com/crimson206/langgraph-dev-tool/issues
Classifier: Development Status :: 2 - Pre-Alpha
Classifier: Programming Language :: Python :: 3
Classifier: Programming Language :: Python :: 3.10
Classifier: Programming Language :: Python :: 3.11
Classifier: Programming Language :: Python :: 3.12
Classifier: Intended Audience :: Developers
Classifier: Topic :: Software Development :: Libraries :: Python Modules
Classifier: License :: OSI Approved :: MIT License
Classifier: Operating System :: OS Independent
Classifier: Typing :: Typed
Requires-Python: >=3.10
License-File: LICENSE
Requires-Dist: langgraph
